Workbook

Sheet Inputs
B2: Amortization Patterns — shared inputs
B3: ReFiAI · Unit 3 · The Four Repayment Patterns
B5: Loan amount (PV) | C5: 100000
B6: Annual interest rate | C6: 0.07
B7: Amortization (years) | C7: 30
B8: Monthly rate (i) | C8: =C6/12 -> 0.0058333333
B9: Total months (N) | C9: =C7*12 -> 360

Sheet IO
A1: Mo | B1: Beginning balance | C1: Payment | D1: Interest | E1: Principal | F1: Ending balance
A2: 1 | B2: =Inputs!$C$5 -> 100000 | C2: =D2 -> 583.33333 | D2: =B2*Inputs!$C$8 -> 583.33333 | E2: 0 | F2: =B2-E2 -> 100000
A3: 2 | B3: =F2 -> 100000 | C3: =D3 -> 583.33333 | D3: =B3*Inputs!$C$8 -> 583.33333 | E3: 0 | F3: =B3-E3 -> 100000
A4: 3 | B4: =F3 -> 100000 | C4: =D4 -> 583.33333 | D4: =B4*Inputs!$C$8 -> 583.33333 | E4: 0 | F4: =B4-E4 -> 100000
A5: 4 | B5: =F4 -> 100000 | C5: =D5 -> 583.33333 | D5: =B5*Inputs!$C$8 -> 583.33333 | E5: 0 | F5: =B5-E5 -> 100000
A6: 5 | B6: =F5 -> 100000 | C6: =D6 -> 583.33333 | D6: =B6*Inputs!$C$8 -> 583.33333 | E6: 0 | F6: =B6-E6 -> 100000
A7: 6 | B7: =F6 -> 100000 | C7: =D7 -> 583.33333 | D7: =B7*Inputs!$C$8 -> 583.33333 | E7: 0 | F7: =B7-E7 -> 100000
A8: 7 | B8: =F7 -> 100000 | C8: =D8 -> 583.33333 | D8: =B8*Inputs!$C$8 -> 583.33333 | E8: 0 | F8: =B8-E8 -> 100000
A9: 8 | B9: =F8 -> 100000 | C9: =D9 -> 583.33333 | D9: =B9*Inputs!$C$8 -> 583.33333 | E9: 0 | F9: =B9-E9 -> 100000
A10: 9 | B10: =F9 -> 100000 | C10: =D10 -> 583.33333 | D10: =B10*Inputs!$C$8 -> 583.33333 | E10: 0 | F10: =B10-E10 -> 100000
A11: 10 | B11: =F10 -> 100000 | C11: =D11 -> 583.33333 | D11: =B11*Inputs!$C$8 -> 583.33333 | E11: 0 | F11: =B11-E11 -> 100000
A12: 11 | B12: =F11 -> 100000 | C12: =D12 -> 583.33333 | D12: =B12*Inputs!$C$8 -> 583.33333 | E12: 0 | F12: =B12-E12 -> 100000
A13: 12 | B13: =F12 -> 100000 | C13: =D13 -> 583.33333 | D13: =B13*Inputs!$C$8 -> 583.33333 | E13: 0 | F13: =B13-E13 -> 100000
A14: 13 | B14: =F13 -> 100000 | C14: =D14 -> 583.33333 | D14: =B14*Inputs!$C$8 -> 583.33333 | E14: 0 | F14: =B14-E14 -> 100000
... A360: 359 | B360: =F359 -> 100000 | C360: =D360 -> 583.33333 | D360: =B360*Inputs!$C$8 -> 583.33333 | E360: 0 | F360: =B360-E360 -> 100000
A361: 360 | B361: =F360 -> 100000 | C361: =D361+E361 -> 100583.33 | D361: =B361*Inputs!$C$8 -> 583.33333 | E361: =B361 -> 100000 | F361: =B361-E361 -> 0

Sheet CPM
A1: Mo | B1: Beginning balance | C1: Payment | D1: Interest | E1: Principal | F1: Ending balance
A2: 1 | B2: =Inputs!$C$5 -> 100000 | C2: =-PMT(Inputs!$C$8,Inputs!$C$9,Inputs!$C$5) -> 665.3025 | D2: =B2*Inputs!$C$8 -> 583.33333 | E2: =C2-D2 -> 81.969162 | F2: =B2-E2 -> 99918.031
A3: 2 | B3: =F2 -> 99918.031 | C3: =-PMT(Inputs!$C$8,Inputs!$C$9,Inputs!$C$5) -> 665.3025 | D3: =B3*Inputs!$C$8 -> 582.85518 | E3: =C3-D3 -> 82.447315 | F3: =B3-E3 -> 99835.584
A4: 3 | B4: =F3 -> 99835.584 | C4: =-PMT(Inputs!$C$8,Inputs!$C$9,Inputs!$C$5) -> 665.3025 | D4: =B4*Inputs!$C$8 -> 582.37424 | E4: =C4-D4 -> 82.928258 | F4: =B4-E4 -> 99752.655
A5: 4 | B5: =F4 -> 99752.655 | C5: =-PMT(Inputs!$C$8,Inputs!$C$9,Inputs!$C$5) -> 665.3025 | D5: =B5*Inputs!$C$8 -> 581.89049 | E5: =C5-D5 -> 83.412006 | F5: =B5-E5 -> 99669.243
A6: 5 | B6: =F5 -> 99669.243 | C6: =-PMT(Inputs!$C$8,Inputs!$C$9,Inputs!$C$5) -> 665.3025 | D6: =B6*Inputs!$C$8 -> 581.40392 | E6: =C6-D6 -> 83.898576 | F6: =B6-E6 -> 99585.345
A7: 6 | B7: =F6 -> 99585.345 | C7: =-PMT(Inputs!$C$8,Inputs!$C$9,Inputs!$C$5) -> 665.3025 | D7: =B7*Inputs!$C$8 -> 580.91451 | E7: =C7-D7 -> 84.387985 | F7: =B7-E7 -> 99500.957
A8: 7 | B8: =F7 -> 99500.957 | C8: =-PMT(Inputs!$C$8,Inputs!$C$9,Inputs!$C$5) -> 665.3025 | D8: =B8*Inputs!$C$8 -> 580.42225 | E8: =C8-D8 -> 84.880248 | F8: =B8-E8 -> 99416.076
A9: 8 | B9: =F8 -> 99416.076 | C9: =-PMT(Inputs!$C$8,Inputs!$C$9,Inputs!$C$5) -> 665.3025 | D9: =B9*Inputs!$C$8 -> 579.92711 | E9: =C9-D9 -> 85.375383 | F9: =B9-E9 -> 99330.701
A10: 9 | B10: =F9 -> 99330.701 | C10: =-PMT(Inputs!$C$8,Inputs!$C$9,Inputs!$C$5) -> 665.3025 | D10: =B10*Inputs!$C$8 -> 579.42909 | E10: =C10-D10 -> 85.873406 | F10: =B10-E10 -> 99244.828
A11: 10 | B11: =F10 -> 99244.828 | C11: =-PMT(Inputs!$C$8,Inputs!$C$9,Inputs!$C$5) -> 665.3025 | D11: =B11*Inputs!$C$8 -> 578.92816 | E11: =C11-D11 -> 86.374334 | F11: =B11-E11 -> 99158.453
A12: 11 | B12: =F11 -> 99158.453 | C12: =-PMT(Inputs!$C$8,Inputs!$C$9,Inputs!$C$5) -> 665.3025 | D12: =B12*Inputs!$C$8 -> 578.42431 | E12: =C12-D12 -> 86.878184 | F12: =B12-E12 -> 99071.575
A13: 12 | B13: =F12 -> 99071.575 | C13: =-PMT(Inputs!$C$8,Inputs!$C$9,Inputs!$C$5) -> 665.3025 | D13: =B13*Inputs!$C$8 -> 577.91752 | E13: =C13-D13 -> 87.384974 | F13: =B13-E13 -> 98984.19
A14: 13 | B14: =F13 -> 98984.19 | C14: =-PMT(Inputs!$C$8,Inputs!$C$9,Inputs!$C$5) -> 665.3025 | D14: =B14*Inputs!$C$8 -> 577.40778 | E14: =C14-D14 -> 87.894719 | F14: =B14-E14 -> 98896.295
... A361: 360 | B361: =F360 -> 661.44407 | C361: =-PMT(Inputs!$C$8,Inputs!$C$9,Inputs!$C$5) -> 665.3025 | D361: =B361*Inputs!$C$8 -> 3.8584238 | E361: =C361-D361 -> 661.44407 | F361: =B361-E361 -> 2.8080649e-10

Sheet CAM
A1: Mo | B1: Beginning balance | C1: Payment | D1: Interest | E1: Principal | F1: Ending balance
A2: 1 | B2: =Inputs!$C$5 -> 100000 | C2: =E2+D2 -> 861.11111 | D2: =B2*Inputs!$C$8 -> 583.33333 | E2: =Inputs!$C$5/Inputs!$C$9 -> 277.77778 | F2: =B2-E2 -> 99722.222
A3: 2 | B3: =F2 -> 99722.222 | C3: =E3+D3 -> 859.49074 | D3: =B3*Inputs!$C$8 -> 581.71296 | E3: =Inputs!$C$5/Inputs!$C$9 -> 277.77778 | F3: =B3-E3 -> 99444.444
A4: 3 | B4: =F3 -> 99444.444 | C4: =E4+D4 -> 857.87037 | D4: =B4*Inputs!$C$8 -> 580.09259 | E4: =Inputs!$C$5/Inputs!$C$9 -> 277.77778 | F4: =B4-E4 -> 99166.667
A5: 4 | B5: =F4 -> 99166.667 | C5: =E5+D5 -> 856.25 | D5: =B5*Inputs!$C$8 -> 578.47222 | E5: =Inputs!$C$5/Inputs!$C$9 -> 277.77778 | F5: =B5-E5 -> 98888.889
A6: 5 | B6: =F5 -> 98888.889 | C6: =E6+D6 -> 854.62963 | D6: =B6*Inputs!$C$8 -> 576.85185 | E6: =Inputs!$C$5/Inputs!$C$9 -> 277.77778 | F6: =B6-E6 -> 98611.111
A7: 6 | B7: =F6 -> 98611.111 | C7: =E7+D7 -> 853.00926 | D7: =B7*Inputs!$C$8 -> 575.23148 | E7: =Inputs!$C$5/Inputs!$C$9 -> 277.77778 | F7: =B7-E7 -> 98333.333
A8: 7 | B8: =F7 -> 98333.333 | C8: =E8+D8 -> 851.38889 | D8: =B8*Inputs!$C$8 -> 573.61111 | E8: =Inputs!$C$5/Inputs!$C$9 -> 277.77778 | F8: =B8-E8 -> 98055.556
A9: 8 | B9: =F8 -> 98055.556 | C9: =E9+D9 -> 849.76852 | D9: =B9*Inputs!$C$8 -> 571.99074 | E9: =Inputs!$C$5/Inputs!$C$9 -> 277.77778 | F9: =B9-E9 -> 97777.778
A10: 9 | B10: =F9 -> 97777.778 | C10: =E10+D10 -> 848.14815 | D10: =B10*Inputs!$C$8 -> 570.37037 | E10: =Inputs!$C$5/Inputs!$C$9 -> 277.77778 | F10: =B10-E10 -> 97500
A11: 10 | B11: =F10 -> 97500 | C11: =E11+D11 -> 846.52778 | D11: =B11*Inputs!$C$8 -> 568.75 | E11: =Inputs!$C$5/Inputs!$C$9 -> 277.77778 | F11: =B11-E11 -> 97222.222
A12: 11 | B12: =F11 -> 97222.222 | C12: =E12+D12 -> 844.90741 | D12: =B12*Inputs!$C$8 -> 567.12963 | E12: =Inputs!$C$5/Inputs!$C$9 -> 277.77778 | F12: =B12-E12 -> 96944.444
A13: 12 | B13: =F12 -> 96944.444 | C13: =E13+D13 -> 843.28704 | D13: =B13*Inputs!$C$8 -> 565.50926 | E13: =Inputs!$C$5/Inputs!$C$9 -> 277.77778 | F13: =B13-E13 -> 96666.667
A14: 13 | B14: =F13 -> 96666.667 | C14: =E14+D14 -> 841.66667 | D14: =B14*Inputs!$C$8 -> 563.88889 | E14: =Inputs!$C$5/Inputs!$C$9 -> 277.77778 | F14: =B14-E14 -> 96388.889
... A361: 360 | B361: =F360 -> 277.77778 | C361: =E361+D361 -> 279.39815 | D361: =B361*Inputs!$C$8 -> 1.6203704 | E361: =Inputs!$C$5/Inputs!$C$9 -> 277.77778 | F361: =B361-E361 -> -7.4157924e-10
